mtg_card_puller/__init__.py
mtg_card_puller/cli.py
mtg_card_puller/mtg_card_puller.py
mtg_card_puller-0.0.1.dist-info/METADATA
mtg_card_puller-0.0.1.dist-info/WHEEL
mtg_card_puller-0.0.1.dist-info/entry_points.txt
mtg_card_puller-0.0.1.dist-info/licenses/LICENSE
mtg_card_puller-0.0.1.dist-info/RECORD
