Metadata-Version: 2.4
Name: mtg_card_puller
Version: 0.0.1
Summary: Pull MTG card images in b
Project-URL: Homepage, https://github.com/seerai/mtg_card_puller
Author-email: Rob Fletcher <robroy.fletcher@gmail.com>
License: Apache Software License 2.0
License-File: LICENSE
Classifier: Development Status :: 2 - Pre-Alpha
Classifier: Intended Audience :: Developers
Classifier: License :: OSI Approved :: Apache Software License
Classifier: Natural Language :: English
Classifier: Programming Language :: Python :: 3
Classifier: Programming Language :: Python :: 3.10
Requires-Python: >=3.10
Requires-Dist: click>=7.0
Requires-Dist: geodesic-api
Provides-Extra: dev
Requires-Dist: coverage; extra == 'dev'
Requires-Dist: jupyterlab; extra == 'dev'
Requires-Dist: pre-commit; extra == 'dev'
Requires-Dist: pytest; extra == 'dev'
Requires-Dist: ruff; extra == 'dev'
